{
  "project_info": {
    "project_number": "783425289640",
    "project_id": "stay-safe-c2dfe",
    "storage_bucket": "stay-safe-c2dfe.appspot.com"
  },
  "client": [
    {
      "client_info": {
        "mobilesdk_app_id": "1:783425289640:android:e24edb862ae252dff5719d",
        "android_client_info": {
          "package_name": "com.example.stay_safe"
        }
      },
      "oauth_client": [
        {
          "client_id": "783425289640-md5iugns5kt6opfv9s2tn39u96e81b61.apps.googleusercontent.com",
          "client_type": 3
        }
      ],
      "api_key": [
        {
          "current_key": "AIzaSyCzLhlvOc-AuHts-Jwxm9sesW6hinlDcYI"
        }
      ],
      "services": {
        "appinvite_service": {
          "other_platform_oauth_client": [
            {
              "client_id": "783425289640-md5iugns5kt6opfv9s2tn39u96e81b61.apps.googleusercontent.com",
              "client_type": 3
            }
          ]
        }
      }
    }
  ],
  "configuration_version": "1"
}